cms_figure/__init__.py
cms_figure/labels.py
cms_figure/tdr_style.py
cms_figure/utils.py
cms_figure-0.9.0.dist-info/DESCRIPTION.rst
cms_figure-0.9.0.dist-info/METADATA
cms_figure-0.9.0.dist-info/RECORD
cms_figure-0.9.0.dist-info/WHEEL
cms_figure-0.9.0.dist-info/metadata.json
cms_figure-0.9.0.dist-info/top_level.txt
