Metadata-Version: 2.0
Name: cms-figure
Version: 0.9.0
Summary: Styling and labels for CMS figures produced using ROOT
Home-page: https://github.com/swang373/cms_figure
Author: Sean-Jiun Wang
Author-email: sean.jiun.wang@gmail.com
License: MIT
Download-URL: https://github.com/swang373/cms_figure/tarball/0.9.0
Platform: UNKNOWN
Classifier: Development Status :: 4 - Beta
Classifier: Intended Audience :: Developers
Classifier: Intended Audience :: Science/Research
Classifier: License :: OSI Approved :: MIT License
Classifier: Operating System :: MacOS
Classifier: Operating System :: POSIX
Classifier: Operating System :: Unix
Classifier: Programming Language :: Python
Classifier: Programming Language :: Python :: 2.7
Classifier: Topic :: Scientific/Engineering
Classifier: Topic :: Scientific/Engineering :: Physics
Classifier: Topic :: Scientific/Engineering :: Visualization
Classifier: Topic :: Software Development
Classifier: Topic :: Utilities
Requires-Python: >=2.7, <3
